{
  "styles/banners.css": "styles/banners.c9394ab2.css",
  "styles/dobrevety.css": "styles/dobrevety.ae6dc5c3.css",
  "styles/gallery.css": "styles/gallery.25caabf2.css",
  "styles/knihy-roka.css": "styles/knihy-roka.ef3998bb.css",
  "styles/light.css": "styles/light.9a2349d8.css",
  "styles/main.css": "styles/main.338b51f0.css",
  "styles/review-cards.css": "styles/review-cards.393bd0bf.css",
  "fonts/Tabac/fonts.css": "fonts/Tabac/fonts.1f89903e.css",
  "fonts/Tabac-Sans/style.css": "fonts/Tabac-Sans/style.b0d0f9cd.css",
  "fonts/opensans/fonts.css": "fonts/opensans/fonts.f3e271ed.css",
  "scripts/charts.js": "scripts/charts.6b4d4825.js",
  "scripts/gallery.js": "scripts/gallery.1ecd024f.js",
  "scripts/html3d.js": "scripts/html3d.69a3e1ef.js",
  "scripts/knizna-odysea.js": "scripts/knizna-odysea.47320e25.js",
  "scripts/light.js": "scripts/light.a2991ef9.js",
  "scripts/main.js": "scripts/main.70a45ec0.js",
  "scripts/vendor.js": "scripts/vendor.bff8214d.js",
  "scripts/plugins/modernizr.js": "scripts/plugins/modernizr.4a489747.js"
}